sqlcontroller/__init__.py
sqlcontroller/controller.py
sqlcontroller/field.py
sqlcontroller/querybuilder.py
sqlcontroller/row_conversion.py
sqlcontroller/table.py
sqlcontroller/validator.py
sqlcontroller-0.1.8.dist-info/LICENSE
sqlcontroller-0.1.8.dist-info/METADATA
sqlcontroller-0.1.8.dist-info/WHEEL
sqlcontroller-0.1.8.dist-info/top_level.txt
sqlcontroller-0.1.8.dist-info/RECORD
